{
	"format_version": "1.9.0",
	"credit": "Made by Cart3r using Blockbench.",
	"texture_size": [32, 32],
	"textures": {
		"0": "portalcubed:portal_gun/captchalogue_card",
		"2": "portalcubed:portal_gun/captchalogue_card_back",
		"3": "portalcubed:portal_gun/captchalogue_card_overlay",
		"4": "portalcubed:portal_gun/captchalogue_card_back_overlay",
		"particle": "portalcubed:portal_gun/captchalogue_card"
	},
	"elements": [
		{
			"from": [0, 0, 8],
			"to": [16, 16, 8],
			"rotation": {"angle": 0, "axis": "y", "origin": [8, 8, 8]},
			"faces": {
				"north": {"uv": [0, 0, 16, 16], "texture": "#2", "tintindex": 1},
				"south": {"uv": [0, 0, 16, 16], "texture": "#0", "tintindex": 1}
			}
		},
		{
			"from": [0, 0, 8],
			"to": [16, 16, 8],
			"rotation": {"angle": 0, "axis": "y", "origin": [8, 8, 8]},
			"faces": {
				"north": {"uv": [0, 0, 16, 16], "texture": "#4"},
				"south": {"uv": [0, 0, 16, 16], "texture": "#3"}
			}
		}
	],
	"gui_light": "front",
	"display": {
		"thirdperson_righthand": {
			"translation": [0, 3, 1],
			"scale": [0.55, 0.55, 0.55]
		},
		"thirdperson_lefthand": {
			"translation": [0, 3, 1],
			"scale": [0.55, 0.55, 0.55]
		},
		"firstperson_righthand": {
			"rotation": [0, -90, 25],
			"translation": [1.13, 3.2, 1.13],
			"scale": [0.68, 0.68, 0.68]
		},
		"firstperson_lefthand": {
			"rotation": [0, -90, 25],
			"translation": [1.13, 3.2, 1.13],
			"scale": [0.68, 0.68, 0.68]
		},
		"ground": {
			"translation": [0, 3, -0.05],
			"scale": [0.5, 0.5, 0.5]
		},
		"gui": {
			"translation": [0.75, 1, -5],
			"scale": [1.75, 1.75, 1.75]
		},
		"head": {
			"rotation": [0, -180, 0],
			"translation": [0, 13, 7]
		},
		"fixed": {
			"rotation": [0, -180, 0]
		}
	}
}
