{
  "name": {
    "translate": "portal_type.portalcubed.pipis"
  },
  "default_primary_color": 49151,
  "default_secondary_color": 16776960,
  "sounds": {
    "shared": {
      "open": "minecraft:block.sniffer_egg.plop",
      "cant_open": "minecraft:block.sniffer_egg.crack",
      "close": "minecraft:entity.turtle.lay_egg",
      "travel": "minecraft:block.sniffer_egg.plop"
    }
  },
  "textures": {
    "open": "portalcubed:portal/pipis/pipis_open",
    "closed": "portalcubed:portal/pipis/pipis",
    "tracer": [
      {
      "texture": "portalcubed:portal/pipis/pipis_tracer",
      "tint": true
      },
      {
      "texture": "portalcubed:portal/pipis/pipis_tracer_overlay",
      "tint": false
      }
    ]
  },
  "stencil": "portalcubed:portal/pipis/pipis_stencil"
}
