{
  "name": {
    "translate": "portal_type.portalcubed.player_shaped_hole"
  },
  "default_primary_color": 0,
  "default_secondary_color": 0,
  "sounds": {
    "shared": {
      "open": "minecraft:block.deepslate.break",
      "close": "minecraft:block.deepslate.place",
      "travel": "minecraft:block.deepslate.step"
    }
  },
  "textures": {
    "open": [
      {
      "texture": "portalcubed:portal/player_shaped_hole/player_shaped_hole_overlay",
      "tint": false
      }
    ],
    "closed": [
      {
        "texture": "portalcubed:portal/player_shaped_hole/player_shaped_hole",
        "tint": true
      },
      {
        "texture": "portalcubed:portal/player_shaped_hole/player_shaped_hole_overlay",
        "tint": false
      }
    ],
    "tracer": "portalcubed:portal/player_shaped_hole/player_shaped_hole_tracer"
  },
  "stencil": "portalcubed:portal/player_shaped_hole/player_shaped_hole_stencil",
  "place_animation": {
    "type": "pop_in",
    "easing": "linear",
    "duration": 1
  }
}
