{
	"credit": "Made by Cart3r using Blockbench.",
	"texture_size": [32, 32],
	"textures": {
		"0": "portalcubed:block/pedestal_button",
		"2": "portalcubed:block/pedestal_button_e",
		"particle": "portalcubed:block/smooth_gray_panel"
	},
	"elements": [
		{
			"from": [3.5, 0, 3.5],
			"to": [12.5, 1, 12.5],
			"faces": {
				"north": {"uv": [15.984, 11.016, 11.516, 11.484], "texture": "#0"},
				"east": {"uv": [15.984, 11.016, 11.516, 11.484], "texture": "#0"},
				"south": {"uv": [15.984, 11.016, 11.516, 11.484], "texture": "#0"},
				"west": {"uv": [15.984, 11.016, 11.516, 11.484], "texture": "#0"},
				"up": {"uv": [11.516, 6.016, 15.984, 10.484], "texture": "#0"},
				"down": {"uv": [11.516, 6.016, 15.984, 10.484], "texture": "#0", "cullface": "down"}
			}
		},
		{
			"from": [4, 1.025, 4],
			"to": [12, 2.025, 12],
			"rotation": {"angle": 0, "axis": "y", "origin": [8, 8.925, 8]},
			"faces": {
				"north": {"uv": [0.016, 15.516, 3.984, 15.984], "texture": "#0"},
				"east": {"uv": [0.016, 15.516, 3.984, 15.984], "texture": "#0"},
				"south": {"uv": [0.016, 15.516, 3.984, 15.984], "texture": "#0"},
				"west": {"uv": [0.016, 15.516, 3.984, 15.984], "texture": "#0"},
				"up": {"uv": [0.016, 12.016, 3.984, 15.984], "texture": "#0"},
				"down": {"uv": [0.016, 12.016, 3.984, 15.984], "texture": "#0", "cullface": "down"}
			}
		},
		{
			"from": [5.5, 2.025, 5.5],
			"to": [10.5, 18.025, 10.5],
			"rotation": {"angle": 0, "axis": "y", "origin": [16, 8.925, 0]},
			"faces": {
				"north": {"uv": [0.016, 0.016, 2.484, 7.984], "texture": "#0"},
				"east": {"uv": [0.016, 0.016, 2.484, 7.984], "texture": "#0"},
				"south": {"uv": [2.516, 0.016, 4.984, 7.984], "texture": "#0"},
				"west": {"uv": [0.016, 0.016, 2.484, 7.984], "texture": "#0"}
			}
		},
		{
			"name": "emission",
			"from": [5.49, 2.015, 5.49],
			"to": [10.51, 19.01, 10.51],
			"rotation": {"angle": 0, "axis": "y", "origin": [16, 8.925, 0]},
			"faces": {
				"north": {"uv": [12.508, 0.008, 14.992, 8.492], "texture": "#2"},
				"east": {"uv": [7.508, 0.008, 9.992, 8.492], "texture": "#2"},
				"south": {"uv": [9.991, 0.025, 12.501, 8.4975], "texture": "#2"},
				"west": {"uv": [7.508, 0.008, 9.992, 8.492], "texture": "#2"}
			}
		},
		{
			"name": "emission",
			"from": [5.49, 18.015, 7.49],
			"to": [10.51, 18.285, 8.51],
			"rotation": {"angle": 0, "axis": "y", "origin": [16, 8.95, 0]},
			"faces": {
				"east": {"uv": [11.016, 1.016, 11.484, 1.484], "rotation": 270, "texture": "#2"},
				"west": {"uv": [11.016, 1.016, 11.484, 1.484], "rotation": 270, "texture": "#2"}
			}
		},
		{
			"from": [5.5, 18.025, 5.5],
			"to": [10.5, 19, 7.5],
			"rotation": {"angle": 0, "axis": "y", "origin": [16, 8.925, 0]},
			"faces": {
				"north": {"uv": [0.016, 0.016, 2.484, 0.484], "texture": "#0"},
				"east": {"uv": [1.516, 0.016, 2.484, 0.484], "texture": "#0"},
				"west": {"uv": [0.016, 0.016, 0.984, 0.484], "texture": "#0"}
			}
		},
		{
			"from": [5.475, 16.25, 1.74],
			"to": [10.525, 17.275, 6.74],
			"rotation": {"angle": 22.5, "axis": "x", "origin": [7.975, 8.175, 10.49712]},
			"faces": {
				"north": {"uv": [0.016, 10.516, 2.484, 10.984], "texture": "#0"},
				"east": {"uv": [0.016, 10.516, 2.484, 10.984], "texture": "#0"},
				"west": {"uv": [0.016, 10.516, 2.484, 10.984], "texture": "#0"},
				"up": {"uv": [0.016, 8.016, 2.484, 10.484], "rotation": 90, "texture": "#0"}
			}
		},
		{
			"from": [5.975, 16.78484, 2.22],
			"to": [9.975, 17.78484, 6.22],
			"rotation": {"angle": 22.5, "axis": "x", "origin": [7.975, 8.175, 10.49712]},
			"faces": {
				"north": {"uv": [6.984, 1.516, 5.016, 1.984], "texture": "#0"},
				"east": {"uv": [5.016, 1.516, 6.984, 1.984], "texture": "#0"},
				"south": {"uv": [6.984, 1.516, 5.016, 1.984], "texture": "#0"},
				"west": {"uv": [5.016, 1.516, 6.984, 1.984], "texture": "#0"},
				"up": {"uv": [5.016, 0.016, 6.984, 1.984], "texture": "#0"}
			}
		}
	],
	"groups": [
		0,
		{
			"name": "pedestal_button",
			"origin": [8, 8, 8],
			"color": 0,
			"children": [1, 2, 3, 4, 5, 6, 7]
		}
	]
}